{
  "meta": {
    "count": 1
  },
  "data": [
    {
      "tags": [
        ""
      ],
      "main_text": "Ohje: Tehtävät liittyvät oheiseen aineistoon. **Valitse viidestä tehtävästä kolme**. Tehtävät arvostellaan pistein 0–6. Vastausta kirjoittaessasi voit lähteä siitä, että lukija tuntee aineiston. Vastauksessa esitetyt havainnot, väitteet ja tulkinnat tulee kuitenkin perustella aineiston avulla. Vastauksen sopiva pituus on noin kaksi sivua. Aloita jokainen vastaus uudelta sivulta. **Anna kullekin vastaustekstillesi otsikko**. Merkitse otsikon eteen myös tehtävän numero. Vastausten tulee olla selvästi ja siististi kirjoitettuja, mutta niitä ei tarvitse kirjoittaa puhtaaksi kuulakynällä tai musteella.\n\n​\n\nHuom.! Tekstien kieliasu on alkuperäisen julkaisun mukainen.\n",
      "characters": null,
      "deleted_at": null,
      "series_uuids": [],
      "questions": [
        {
          "description": null,
          "question_number": null,
          "tags": [],
          "main_text": "Aineisto: [LINK url=https://yle.fi/progressive/fynd/abitreenit/yokoe\\_pdf\\_aineistot/aidinkieli\\_tekstitaito\\_k\\_2012\\_2.pdf|text=Maria Jotuni: Untako lienee (novelli)]\n",
          "deleted_at": null,
          "feedback": "",
          "exam_id": 14556,
          "content": {
            "text": "Aineisto: [LINK url=https://yle.fi/progressive/fynd/abitreenit/yokoe\\_pdf\\_aineistot/aidinkieli\\_tekstitaito\\_k\\_2012\\_2.pdf|text=Maria Jotuni: Untako lienee (novelli)]\n"
          },
          "images": null,
          "settings": {},
          "child_ids": [],
          "classification": null,
          "level": 1,
          "updated_at": "2023-07-17T08:27:43.632727",
          "max_score": null,
          "groupping": null,
          "id": 452535,
          "question_type": "TEXT",
          "options": [],
          "uuid": "d699febc-96e9-45c4-8722-0bec682a4c3f",
          "order_number": 1,
          "multipart": true,
          "created_at": "2017-07-04T07:04:53.492117"
        },
        {
          "description": null,
          "question_number": null,
          "tags": [],
          "main_text": "Aineisto: [LINK url=https://yle.fi/progressive/fynd/abitreenit/yokoe\\_pdf\\_aineistot/aidinkieli\\_tekstitaito\\_k\\_2012\\_2.pdf|text=Maria Jotuni: Untako lienee (novelli)]\n",
          "deleted_at": null,
          "feedback": "",
          "exam_id": 14556,
          "content": {
            "text": "Aineisto: [LINK url=https://yle.fi/progressive/fynd/abitreenit/yokoe\\_pdf\\_aineistot/aidinkieli\\_tekstitaito\\_k\\_2012\\_2.pdf|text=Maria Jotuni: Untako lienee (novelli)]\n"
          },
          "images": null,
          "settings": {},
          "child_ids": [],
          "classification": null,
          "level": 1,
          "updated_at": "2023-07-17T08:27:43.619262",
          "max_score": null,
          "groupping": null,
          "id": 452536,
          "question_type": "TEXT",
          "options": [],
          "uuid": "e86a0985-c69c-4da5-b7a5-eda4e7d398e8",
          "order_number": 1,
          "multipart": true,
          "created_at": "2017-07-04T07:04:53.495016"
        },
        {
          "description": null,
          "question_number": null,
          "tags": [],
          "main_text": "Tutki Iisakki Kiemungin kolumnin tyylivalintoja ja arvioi niiden onnistuneisuutta.\n",
          "deleted_at": null,
          "feedback": "",
          "exam_id": 14556,
          "content": {
            "text": "Tutki Iisakki Kiemungin kolumnin tyylivalintoja ja arvioi niiden onnistuneisuutta.\n"
          },
          "images": null,
          "settings": {
            "textareaSize": "20"
          },
          "child_ids": [],
          "classification": null,
          "level": 1,
          "updated_at": "2023-07-17T08:27:43.617048",
          "max_score": null,
          "groupping": null,
          "id": 452546,
          "question_type": "ESSAY_QUESTION",
          "options": [],
          "uuid": "0867e241-84e9-4a2e-b716-8202f32e6fb1",
          "order_number": 2,
          "multipart": true,
          "created_at": "2017-07-04T07:04:53.528023"
        },
        {
          "description": null,
          "question_number": null,
          "tags": [
            "18-217329",
            "18-205179"
          ],
          "main_text": null,
          "deleted_at": null,
          "feedback": "",
          "exam_id": 14556,
          "content": {
            "displayNumber": "5."
          },
          "images": null,
          "settings": {
            "material": true
          },
          "child_ids": [
            "6f61c77a-36b7-4406-8843-e5b388079367",
            "1c30ce9c-9e91-4c79-bf21-a02c9611e0de"
          ],
          "classification": null,
          "level": 0,
          "updated_at": "2023-07-17T08:27:43.612471",
          "max_score": null,
          "groupping": null,
          "id": 452534,
          "question_type": "EXAM_QUESTION",
          "options": [],
          "uuid": "52864985-fbb2-407a-b224-96c7aa090a3a",
          "order_number": 5,
          "multipart": true,
          "created_at": "2017-07-04T07:04:53.489224"
        },
        {
          "description": null,
          "question_number": null,
          "tags": [
            "18-213064",
            "18-213871",
            "18-2375"
          ],
          "main_text": null,
          "deleted_at": null,
          "feedback": "",
          "exam_id": 14556,
          "content": {
            "displayNumber": "2."
          },
          "images": null,
          "settings": {},
          "child_ids": [
            "d699febc-96e9-45c4-8722-0bec682a4c3f",
            "8cac7705-6b6d-4430-b34e-1dd18566d98b"
          ],
          "classification": null,
          "level": 0,
          "updated_at": "2023-07-17T08:27:43.608236",
          "max_score": null,
          "groupping": null,
          "id": 452532,
          "question_type": "EXAM_QUESTION",
          "options": [],
          "uuid": "36b82ab0-69c9-40be-813e-6fdd8ff5f0c4",
          "order_number": 2,
          "multipart": true,
          "created_at": "2017-07-04T07:04:53.483576"
        },
        {
          "description": null,
          "question_number": null,
          "tags": [
            "18-206608",
            "18-218539",
            "18-213871",
            "18-213925"
          ],
          "main_text": null,
          "deleted_at": null,
          "feedback": "",
          "exam_id": 14556,
          "content": {
            "displayNumber": "4."
          },
          "images": null,
          "settings": {
            "material": true
          },
          "child_ids": [
            "900dbb0d-92b7-4087-b5c0-4867dd7132f5",
            "7b8d18ca-e487-464c-aaad-7a1d374583f0"
          ],
          "classification": null,
          "level": 0,
          "updated_at": "2023-07-17T08:27:43.610479",
          "max_score": null,
          "groupping": null,
          "id": 452533,
          "question_type": "EXAM_QUESTION",
          "options": [],
          "uuid": "82a72ede-f796-47bd-83d2-430090dc176a",
          "order_number": 4,
          "multipart": true,
          "created_at": "2017-07-04T07:04:53.486683"
        },
        {
          "description": null,
          "question_number": null,
          "tags": [],
          "main_text": "Millä keinoin Aktian vakuutusmainos myy turvallisuutta?\n",
          "deleted_at": null,
          "feedback": "",
          "exam_id": 14556,
          "content": {
            "text": "Millä keinoin Aktian vakuutusmainos myy turvallisuutta?\n"
          },
          "images": null,
          "settings": {
            "textareaSize": "20"
          },
          "child_ids": [],
          "classification": null,
          "level": 1,
          "updated_at": "2023-07-17T08:27:43.614876",
          "max_score": null,
          "groupping": null,
          "id": 452542,
          "question_type": "ESSAY_QUESTION",
          "options": [],
          "uuid": "1c30ce9c-9e91-4c79-bf21-a02c9611e0de",
          "order_number": 2,
          "multipart": true,
          "created_at": "2017-07-04T07:04:53.51074"
        },
        {
          "description": null,
          "question_number": null,
          "tags": [],
          "main_text": "Aineisto: [LINK url=https://yle.fi/progressive/fynd/abitreenit/yokoe\\_pdf\\_aineistot/aidinkieli\\_tekstitaito\\_k\\_2012\\_5.pdf|text=Aktian henkivakuutus (mainos)]\n",
          "deleted_at": null,
          "feedback": "",
          "exam_id": 14556,
          "content": {
            "text": "Aineisto: [LINK url=https://yle.fi/progressive/fynd/abitreenit/yokoe\\_pdf\\_aineistot/aidinkieli\\_tekstitaito\\_k\\_2012\\_5.pdf|text=Aktian henkivakuutus (mainos)]\n"
          },
          "images": null,
          "settings": {},
          "child_ids": [],
          "classification": null,
          "level": 1,
          "updated_at": "2023-07-17T08:27:43.620981",
          "max_score": null,
          "groupping": null,
          "id": 452538,
          "question_type": "TEXT",
          "options": [],
          "uuid": "6f61c77a-36b7-4406-8843-e5b388079367",
          "order_number": 1,
          "multipart": true,
          "created_at": "2017-07-04T07:04:53.500418"
        },
        {
          "description": null,
          "question_number": null,
          "tags": [
            "18-93651",
            "18-33949",
            "18-213871"
          ],
          "main_text": null,
          "deleted_at": null,
          "feedback": "",
          "exam_id": 14556,
          "content": {
            "displayNumber": "3."
          },
          "images": null,
          "settings": {
            "material": true
          },
          "child_ids": [
            "e86a0985-c69c-4da5-b7a5-eda4e7d398e8",
            "52b737d5-ce68-4844-a0f9-373807fd31ba"
          ],
          "classification": null,
          "level": 0,
          "updated_at": "2023-07-17T08:27:43.622592",
          "max_score": null,
          "groupping": null,
          "id": 452544,
          "question_type": "EXAM_QUESTION",
          "options": [],
          "uuid": "99279275-9f6c-4b69-8e5e-ae363b1947ba",
          "order_number": 3,
          "multipart": true,
          "created_at": "2017-07-04T07:04:53.522933"
        },
        {
          "description": null,
          "question_number": null,
          "tags": [],
          "main_text": "Mitä romantiikan ja realismin piirteitä on Maria Jotunin novellissa _Untako lienee_? \n",
          "deleted_at": null,
          "feedback": "",
          "exam_id": 14556,
          "content": {
            "text": "Mitä romantiikan ja realismin piirteitä on Maria Jotunin novellissa _Untako lienee_? \n"
          },
          "images": null,
          "settings": {
            "textareaSize": "20"
          },
          "child_ids": [],
          "classification": null,
          "level": 1,
          "updated_at": "2023-07-17T08:27:43.62454",
          "max_score": null,
          "groupping": null,
          "id": 452540,
          "question_type": "ESSAY_QUESTION",
          "options": [],
          "uuid": "52b737d5-ce68-4844-a0f9-373807fd31ba",
          "order_number": 2,
          "multipart": true,
          "created_at": "2017-07-04T07:04:53.505576"
        },
        {
          "description": null,
          "question_number": null,
          "tags": [],
          "main_text": "Vertaile Jotunin novellin ja Forssellin artikkelin käsityksiä parisuhteesta.\n",
          "deleted_at": null,
          "feedback": "",
          "exam_id": 14556,
          "content": {
            "text": "Vertaile Jotunin novellin ja Forssellin artikkelin käsityksiä parisuhteesta.\n"
          },
          "images": null,
          "settings": {
            "textareaSize": "20"
          },
          "child_ids": [],
          "classification": null,
          "level": 1,
          "updated_at": "2023-07-17T08:27:43.627031",
          "max_score": null,
          "groupping": null,
          "id": 452541,
          "question_type": "ESSAY_QUESTION",
          "options": [],
          "uuid": "7b8d18ca-e487-464c-aaad-7a1d374583f0",
          "order_number": 2,
          "multipart": true,
          "created_at": "2017-07-04T07:04:53.508063"
        },
        {
          "description": null,
          "question_number": null,
          "tags": [
            "18-210076",
            "18-215844",
            "18-219482"
          ],
          "main_text": "",
          "deleted_at": null,
          "feedback": "",
          "exam_id": 14556,
          "content": {
            "text": "",
            "displayNumber": "1."
          },
          "images": null,
          "settings": {
            "material": true
          },
          "child_ids": [
            "264917fd-6221-4b9a-a73c-80fc39d49ae2",
            "0867e241-84e9-4a2e-b716-8202f32e6fb1"
          ],
          "classification": null,
          "level": 0,
          "updated_at": "2023-07-17T08:27:43.630451",
          "max_score": null,
          "groupping": null,
          "id": 452543,
          "question_type": "EXAM_QUESTION",
          "options": [],
          "uuid": "31f5eb68-df34-4975-a6bf-04a7153d656c",
          "order_number": 1,
          "multipart": true,
          "created_at": "2017-07-04T07:04:53.519204"
        },
        {
          "description": null,
          "question_number": null,
          "tags": [],
          "main_text": "Mitä Maria Jotunin novelli _Untako lienee_ kertoo avioliiton merkityksestä ja puolison valinnasta 1900-luvun alussa?\n",
          "deleted_at": null,
          "feedback": "",
          "exam_id": 14556,
          "content": {
            "text": "Mitä Maria Jotunin novelli _Untako lienee_ kertoo avioliiton merkityksestä ja puolison valinnasta 1900-luvun alussa?\n"
          },
          "images": null,
          "settings": {
            "textareaSize": "20"
          },
          "child_ids": [],
          "classification": null,
          "level": 1,
          "updated_at": "2023-07-17T08:27:43.635575",
          "max_score": null,
          "groupping": null,
          "id": 452539,
          "question_type": "ESSAY_QUESTION",
          "options": [],
          "uuid": "8cac7705-6b6d-4430-b34e-1dd18566d98b",
          "order_number": 2,
          "multipart": true,
          "created_at": "2017-07-04T07:04:53.503069"
        },
        {
          "description": null,
          "question_number": null,
          "tags": [],
          "main_text": "Aineisto: [LINK url=https://yle.fi/progressive/fynd/abitreenit/yokoe\\_pdf\\_aineistot/aidinkieli\\_tekstitaito\\_k\\_2012\\_1.pdf|text=Iisakki Kiemunki: Tilastollisesti maapallon onnellisin (kolumni)]\n",
          "deleted_at": null,
          "feedback": "",
          "exam_id": 14556,
          "content": {
            "text": "Aineisto: [LINK url=https://yle.fi/progressive/fynd/abitreenit/yokoe\\_pdf\\_aineistot/aidinkieli\\_tekstitaito\\_k\\_2012\\_1.pdf|text=Iisakki Kiemunki: Tilastollisesti maapallon onnellisin (kolumni)]\n"
          },
          "images": null,
          "settings": {},
          "child_ids": [],
          "classification": null,
          "level": 1,
          "updated_at": "2023-07-17T08:27:43.637681",
          "max_score": null,
          "groupping": null,
          "id": 452545,
          "question_type": "TEXT",
          "options": [],
          "uuid": "264917fd-6221-4b9a-a73c-80fc39d49ae2",
          "order_number": 1,
          "multipart": true,
          "created_at": "2017-07-04T07:04:53.525398"
        },
        {
          "description": null,
          "question_number": null,
          "tags": [],
          "main_text": "Aineisto: [LINK url=https://yle.fi/progressive/fynd/abitreenit/yokoe\\_pdf\\_aineistot/aidinkieli\\_tekstitaito\\_k\\_2012\\_2.pdf|text=Maria Jotuni: Untako lienee (novelli)]\n\n[LINK url=https://yle.fi/progressive/fynd/abitreenit/yokoe\\_pdf\\_aineistot/aidinkieli\\_tekstitaito\\_k\\_2012\\_4.pdf|text=Jarno Forssell: Nuori surffaa kevytsuhteissa - ellei parempaa ole näkyvissä (artikkeli)]\n",
          "deleted_at": null,
          "feedback": "",
          "exam_id": 14556,
          "content": {
            "text": "Aineisto: [LINK url=https://yle.fi/progressive/fynd/abitreenit/yokoe\\_pdf\\_aineistot/aidinkieli\\_tekstitaito\\_k\\_2012\\_2.pdf|text=Maria Jotuni: Untako lienee (novelli)]\n\n[LINK url=https://yle.fi/progressive/fynd/abitreenit/yokoe\\_pdf\\_aineistot/aidinkieli\\_tekstitaito\\_k\\_2012\\_4.pdf|text=Jarno Forssell: Nuori surffaa kevytsuhteissa - ellei parempaa ole näkyvissä (artikkeli)]\n"
          },
          "images": null,
          "settings": {},
          "child_ids": [],
          "classification": null,
          "level": 1,
          "updated_at": "2023-07-17T08:27:43.639498",
          "max_score": null,
          "groupping": null,
          "id": 452537,
          "question_type": "TEXT",
          "options": [],
          "uuid": "900dbb0d-92b7-4087-b5c0-4867dd7132f5",
          "order_number": 1,
          "multipart": true,
          "created_at": "2017-07-04T07:04:53.497723"
        }
      ],
      "name": "Äidinkieli, suomi, lukutaidon koe kevät 2012",
      "settings": {},
      "exam_type": "yo-koe",
      "classification": {
        "category": "",
        "exam_type": "yo-koe",
        "year": "2012",
        "language": "fi-FI",
        "show_exam_series": false,
        "force_yletunnus": false,
        "subject": "äidinkieli-suomi-lukutaidon-koe",
        "published": true,
        "semester": "spring"
      },
      "published_at": "2017-07-04T07:04:53.479Z",
      "language": "fi-FI",
      "id": 14556,
      "reviews": [],
      "is_open": true,
      "uuid": "a71eeb10-fac3-43fe-9c47-19cd32b00bf4"
    }
  ]
}